bsmplot/__init__.py
bsmplot/__main__.py
bsmplot/mainframe.py
bsmplot/mainframexpm.py
bsmplot/version.py
bsmplot/bsm/__init__.py
bsmplot/bsm/bsmbackend.py
bsmplot/bsm/csvs.py
bsmplot/bsm/debugtool.py
bsmplot/bsm/editor.py
bsmplot/bsm/glsurface.py
bsmplot/bsm/graph.py
bsmplot/bsm/h5.py
bsmplot/bsm/mat.py
bsmplot/bsm/misctools.py
bsmplot/bsm/nc.py
bsmplot/bsm/parsetab.py
bsmplot/bsm/shell.py
bsmplot/bsm/ulog.py
bsmplot/bsm/utility.py
bsmplot/bsm/vcds.py
bsmplot/bsm/zmqs.py
bsmplot/ico/mainframe.icns
bsmplot/ico/mainframe.ico
bsmplot/ico/mainframe.svg
bsmplot/pvcd/lextab.py
bsmplot/pvcd/parsetab.py
bsmplot/pvcd/pvcd.py
bsmplot/pvcd/pvcd2.py
bsmplot-0.4.0.dist-info/licenses/LICENSE
bsmplot-0.4.0.dist-info/METADATA
bsmplot-0.4.0.dist-info/WHEEL
bsmplot-0.4.0.dist-info/entry_points.txt
bsmplot-0.4.0.dist-info/top_level.txt
bsmplot-0.4.0.dist-info/RECORD
