Metadata-Version: 2.4
Name: bsmplot
Version: 0.4.0
Summary: bsmplot is a tool to visualize time series
Author-email: Tianzhu Qiao <tq@feiyilin.com>
License: MIT License
Project-URL: Homepage, https://github.com/tianzhuqiao/bsmplot
Classifier: Operating System :: OS Independent
Requires-Python: >=3.0
License-File: LICENSE
Requires-Dist: wxpython>=4.2.1
Requires-Dist: matplotlib>=3.8.1
Requires-Dist: numpy
Requires-Dist: scipy
Requires-Dist: click>=8.1
Requires-Dist: pandas
Requires-Dist: pyulog
Requires-Dist: mplpanel>=0.2.4
Requires-Dist: aui2>=0.2.0
Requires-Dist: zmq
Requires-Dist: netCDF4
Requires-Dist: bsmutility>=0.3.9
Requires-Dist: ply
Requires-Dist: charset_normalizer
Requires-Dist: h5py
Requires-Dist: packaging
Dynamic: license-file
